hijri_datetime/__init__.py
hijri_datetime/_version.py
hijri_datetime/calendar.py
hijri_datetime/constants.py
hijri_datetime/conversion.py
hijri_datetime/date.py
hijri_datetime/datetime.py
hijri_datetime/exceptions.py
hijri_datetime/hello.py
hijri_datetime/range.py
hijri_datetime/time.py
hijri_datetime/utils.py
hijri_datetime-0.2.3.post0.dist-info/LICENSE
hijri_datetime-0.2.3.post0.dist-info/METADATA
hijri_datetime-0.2.3.post0.dist-info/WHEEL
hijri_datetime-0.2.3.post0.dist-info/top_level.txt
hijri_datetime-0.2.3.post0.dist-info/RECORD
